google_suite/__init__.py
google_suite/blogger.py
google_suite/gmail.py
google_suite/models/__init__.py
google_suite/models/gmail_models.py
google_suite/models/gsuite_models.py
google_suite/utils/__init__.py
google_suite/utils/util.py
google_suite-0.1.4.dist-info/METADATA
google_suite-0.1.4.dist-info/WHEEL
google_suite-0.1.4.dist-info/RECORD
